{
  "caseId": "case-partnership-03",
  "dialogues": [
    {
      "speaker": "system",
      "text": "초기 진술이 끝나자 캘린더 수정과 단독 덱 출력의 선후관계를 두고 반박이 시작된다.",
      "relatedDisputes": [],
      "behaviorHint": null
    },
    {
      "speaker": "b",
      "text": "도윤씨, 아까 'IR 컨설턴트 메일이 밤 11시 20분에 왔다'고 했잖아요. 근데 그 메일에 '오프닝을 도윤씨로 바꿔라'라는 말은 없었어요. 저도 참조에 있었거든요. 흐름 최적화가 아니라 도윤씨의 판단이었잖아요.",
      "relatedDisputes": [
        "d-1",
        "d-4"
      ],
      "behaviorHint": "Phase 1에서 넘어간 IR 메일의 실제 내용을 처음으로 정면 반박한다."
    },
    {
      "speaker": "a",
      "text": "서린씨, 메일 본문에 '제품 데모를 앞단에 배치하면 투자자 집중도가 올라간다'는 문장이 있었습니다. 그걸 반영한 거고, 투자자 관점에서 기술 오프닝이 효율적이었습니다.",
      "relatedDisputes": [
        "d-1",
        "d-5"
      ],
      "behaviorHint": "메일 문장을 인용하며 효율 프레임을 유지하지만 목소리가 약간 빨라진다."
    },
    {
      "speaker": "b",
      "text": "'앞단에 배치'가 '도윤씨가 오프닝을 한다'는 뜻이에요? 도윤씨, 전날 밤 10시까지 캘린더에 확정하기로 했잖아요. 아까도 말했지만 그걸 새벽에 혼자 바꾼 거잖아요. 확인도 안 하고요.",
      "relatedDisputes": [
        "d-4",
        "d-1"
      ],
      "behaviorHint": "같은 질문을 되묻듯 짧게 반복하며 약속 위반의 핵심을 다시 못 박는다."
    },
    {
      "speaker": "a",
      "text": "... 서린씨, 그런데 서린씨도 오전 7시에 단독 발표용 덱을 출력했잖아요. 거기 제 이름이 빠져 있었어요. 서린씨가 들러리로 만들려 한 건 아닌지 — 재판관님, 시간순서를 보시면 양쪽 다 단독 행동을 했습니다.",
      "relatedDisputes": [
        "d-2",
        "d-3"
      ],
      "behaviorHint": "새벽 수정에 대한 답변을 흐리고 상대의 단독 덱 출력으로 반격한다."
    },
    {
      "speaker": "b",
      "text": "강도윤 씨! 그 덱은 제가 원래 맡고 있던 시장 파트예요. 이름이 빠진 건 작업 중간 버전이었고, 도윤씨처럼 공유 캘린더를 새벽에 바꾼 것과 차원이 다릅니다. 재판관님, 캘린더는 양쪽 다 보는 거예요. 그걸 몰래 바꾼 건 약속을 깬 겁니다.",
      "relatedDisputes": [
        "d-2",
        "d-4"
      ],
      "behaviorHint": "목소리가 올라가며 '차원이 다르다'는 프레임을 세운다. 의자에서 앞으로 몸을 기울인다."
    },
    {
      "speaker": "system",
      "text": "IR 메일에 발표자 지정이 있었는지 여부, 단독 덱 출력과 캘린더 수정의 무게 차이 — 양쪽 모두 상대의 빈틈을 찌르고 있지만 누가 먼저 약속을 깼는지는 아직 분명하지 않다.",
      "relatedDisputes": [
        "d-1",
        "d-2",
        "d-4"
      ],
      "behaviorHint": null
    }
  ]
}