{
  "caseId": "case-workplace-11",
  "dialogues": [
    {
      "speaker": "system",
      "text": "둘 다 상대가 핵심을 흐린다고 말합니다. 한쪽은 이름 삭제를, 다른 쪽은 자료 전달 의심을 먼저 보라고 합니다.",
      "relatedDisputes": [],
      "behaviorHint": null
    },
    {
      "speaker": "a",
      "text": "제 이름이 빠진 표가 먼저 나오지 않았다면 저는 브로커 얘기까지 이렇게 의심하지 않았을 겁니다. 그 삭제가 모든 불신의 시작이었어요.",
      "relatedDisputes": [
        "d-1",
        "d-4"
      ],
      "behaviorHint": "삭제를 불신의 출발점으로 본다."
    },
    {
      "speaker": "b",
      "text": "저는 반대로 브로커 접촉을 먼저 봐야 한다고 생각합니다. 이름 문제만 붙들면 실제 자료 흐름이 뒤로 밀리고, 그게 오히려 더 위험합니다.",
      "relatedDisputes": [
        "d-2",
        "d-3"
      ],
      "behaviorHint": "브로커 축을 더 우선순위 높게 둔다."
    },
    {
      "speaker": "a",
      "text": "자료 흐름은 따질 수 있습니다. 그래도 출원 직전 발명자 목록을 손댄 책임이 먼저 가려지지 않으면, 이후 판단도 계속 기울어요.",
      "relatedDisputes": [
        "d-1",
        "d-2"
      ],
      "behaviorHint": "발명자 삭제를 선행 책임으로 못 박는다."
    },
    {
      "speaker": "b",
      "text": "삭제 책임을 보더라도 그것만으로 사건이 끝나진 않죠. 태준 씨는 끝까지 자료 반출 의심을 단순 조회처럼 좁히려 합니다.",
      "relatedDisputes": [
        "d-2",
        "d-3"
      ],
      "behaviorHint": "실제 반출 여부를 놓치지 말자고 한다."
    },
    {
      "speaker": "a",
      "text": "재판관님께서는 누가 더 억울한지보다, 누가 먼저 기록을 바꿨는지와 누가 외부로 자료를 돌렸는지를 각각 판단해 주셔야 합니다.",
      "relatedDisputes": [
        "d-1",
        "d-2",
        "d-3"
      ],
      "behaviorHint": "두 축을 분리 판단해 달라고 한다."
    },
    {
      "speaker": "b",
      "text": "그리고 마지막에는 발명자 삭제가 방패였는지도 같이 봐 주십시오. 그 지점이 정리돼야 이 사건이 공 빼앗기인지, 공모 은폐인지 갈립니다.",
      "relatedDisputes": [
        "d-1",
        "d-4"
      ],
      "behaviorHint": "최종 축을 방패 여부로 정리한다."
    }
  ]
}
