{
  "caseId": "case-family-v3-01",
  "dialogues": [
    {
      "speaker": "system",
      "text": "배다른 동생을 평생 못마땅해하던 형은, 치매 어머니가 남긴 유서에서 자기 몫이 40퍼센트라는 걸 보고 무너진다. 동생은 끝까지 담담하다. 그래서 더 수상해 보인다.",
      "relatedDisputes": [],
      "behaviorHint": null
    },
    {
      "speaker": "a",
      "text": "재판관님, '돌아가시기 직전에 쓴 유서가 진짜 어머니 뜻이 맞는지' 먼저 따져야 합니다. 어머니 몸이 편찮으신 틈에 제 동생이 요양원을 드나들더니 유서가 갑자기 60대 40으로 바뀌어 있었습니다.",
      "relatedDisputes": [
        "d-1",
        "d-2"
      ],
      "behaviorHint": "평생 형 노릇 했다는 자부심이 깔린 분노. 밀려난 서러움을 공격으로 바꾸는 태도."
    },
    {
      "speaker": "b",
      "text": "재판관님, 저는 어머니를 보러 간 겁니다. '제가 어머니를 꼬드겨서 유서를 바꿨다'는 식은 곤란합니다. 형이 요양원에 못 오신 건 형 사정이지, 그걸 제 탓으로 돌리시면 안 됩니다.",
      "relatedDisputes": [
        "d-1"
      ],
      "behaviorHint": "감정을 드러내지 않는 단조로운 톤. 사실만 나열하며 선을 긋는다."
    },
    {
      "speaker": "a",
      "text": "재판관님, 방문만 문제가 아닙니다. '그 유서가 정말 어머니 마지막 뜻이 맞느냐'가 핵심입니다. 공증 전 몇 주 동안 제 동생만 어머니 곁에 있었고, 저는 그 자리에 낀 적이 없습니다.",
      "relatedDisputes": [
        "d-1",
        "d-2"
      ],
      "behaviorHint": "쟁점을 유서 비율로 확장하며 배제당한 서러움이 올라온다."
    },
    {
      "speaker": "b",
      "text": "재판관님, 유서 비율은 어머니가 정하신 겁니다. 형이 불만이신 건 이해하지만, '제가 어머니를 조종해서 비율을 바꿨다'고 하시면 저는 드릴 말이 없습니다.",
      "relatedDisputes": [
        "d-2"
      ],
      "behaviorHint": "어머니 뜻을 방패로 세운다. 감정 없이 팩트만 말하는 태도가 더 수상해 보인다."
    },
    {
      "speaker": "a",
      "text": "정후야, 네가 왜 그렇게 자주 갔는지가 핵심이야. 어머니 보러 간 거라고? 그러면서 유서 얘기는 한 번도 안 했어? 솔직히 말해봐, 누가 진짜 어머니를 이용한 건지.",
      "relatedDisputes": [
        "d-5"
      ],
      "behaviorHint": "쌓인 미움이 터지면서 반말로 몰아붙인다. 배다른 동생에 대한 오래된 불신."
    },
    {
      "speaker": "b",
      "text": "형, 나한테 그런 식으로 말하면 나도 참기 어려워. 형이 안 온 자리를 내가 채운 거야. 그걸 이용이라고 부르는 건 형이잖아.",
      "relatedDisputes": [
        "d-5"
      ],
      "behaviorHint": "평소의 무표정이 깨지며 반말로 맞받는다. 억울함이 한 줄에 실린다."
    },
    {
      "speaker": "system",
      "text": "'어머니가 정말 판단할 수 있었는지', '60대 40 유서가 진짜 어머니 뜻인지', '누가 어머니를 이용한 건지' — 세 갈래가 얽혀 있습니다.",
      "relatedDisputes": [
        "d-1",
        "d-2",
        "d-5"
      ],
      "behaviorHint": null
    },
    {
      "speaker": "a",
      "text": "재판관님, '그 유서가 정말 어머니 뜻이 맞는지'부터 확인해 주십시오. 그 과정에서 제 동생이 뭘 했는지가 같이 드러날 겁니다.",
      "relatedDisputes": [
        "d-2",
        "d-1"
      ],
      "behaviorHint": "재판관에게 판정 순서를 요청하며 자기 주장을 한 줄로 정리한다."
    },
    {
      "speaker": "b",
      "text": "재판관님, 저는 어머니 곁에 있었던 일을 숨기지 않겠습니다. 다만 형이 모든 걸 제 탓으로 돌리는 건 받아들이기 어렵습니다. 각각 분리해서 봐 주십시오.",
      "relatedDisputes": [
        "d-1",
        "d-2"
      ],
      "behaviorHint": "감정 없이 공정한 판단을 호소한다. 단조로운 톤이 오히려 진정성을 준다."
    }
  ]
}