{
  "caseId": "case-friend-v3-01",
  "dialogues": [
    {
      "speaker": "system",
      "text": "손절한 전 절친이 내 예비신랑에게 계속 연락한다. 결혼 3주 전, 그 장면만 보면 누구라도 친구가 선을 넘었다고 생각한다.",
      "relatedDisputes": [],
      "behaviorHint": null
    },
    {
      "speaker": "a",
      "text": "재판관님, 제 친구가 제 예비신랑한테 열흘 넘게 전화하고 문자한 건 사실입니다. 결혼 3주 전에요. 집착이 아니면 뭡니까.",
      "relatedDisputes": [
        "d-1"
      ],
      "behaviorHint": "연락 기록을 근거로 들며 확신에 찬 톤으로 시작한다."
    },
    {
      "speaker": "b",
      "text": "재판관님, 저는 꼬시려고 연락한 게 아닙니다. 경고하려고 한 겁니다. 지금은 말씀드리기 어렵지만, 제 친구가 모르는 게 있었습니다.",
      "relatedDisputes": [
        "d-1"
      ],
      "behaviorHint": "연락 사실은 인정하되 목적이 달랐다고 선을 긋는다."
    },
    {
      "speaker": "a",
      "text": "재판관님, 경고라고요? 그러면 왜 저한테 직접 말 안 했습니까. 제 예비신랑한테만 연락한 건 변명이 안 됩니다. 게다가 예전 손절 때도 비슷한 패턴이었습니다.",
      "relatedDisputes": [
        "d-1",
        "d-4"
      ],
      "behaviorHint": "경고 주장을 반박하며 과거 손절까지 끌어온다."
    },
    {
      "speaker": "b",
      "text": "재판관님, 예전 손절은 제가 변심해서 된 게 아닙니다. 제 친구가 아시는 것과 실제는 다릅니다. 다만 지금 다 말씀드리기는 어렵습니다.",
      "relatedDisputes": [
        "d-4"
      ],
      "behaviorHint": "과거 손절의 진실을 암시하면서도 구체적으로는 회피한다."
    },
    {
      "speaker": "a",
      "text": "수민아, 도대체 뭘 숨기는 거야? 예전에도 그러더니 지금도 똑같아. 내 예비신랑한테 연락한 것도 모자라서, 나한테는 한마디도 안 하고. 그래서 내가 단톡방에 올린 거야. 다들 알아야 할 것 같아서.",
      "relatedDisputes": [
        "d-5"
      ],
      "behaviorHint": "친구에게 직접 반말로 몰아붙이며 단톡방 공개를 정당화한다."
    },
    {
      "speaker": "b",
      "text": "다은아, 확인도 안 하고 먼저 퍼뜨린 건 너잖아. 나한테 물어보기라도 했어? 그 단톡방 때문에 내 이름이 어떻게 됐는지 알아?",
      "relatedDisputes": [
        "d-5"
      ],
      "behaviorHint": "단톡방 공개에 반말로 맞받아치며 명예 훼손을 지적한다."
    },
    {
      "speaker": "system",
      "text": "예비신랑 연락의 목적, 과거 손절의 이유, 그리고 누가 먼저 상대의 명예를 무너뜨렸는지 — 세 가지 쟁점이 얽혀 있습니다.",
      "relatedDisputes": [
        "d-1",
        "d-4",
        "d-5"
      ],
      "behaviorHint": null
    },
    {
      "speaker": "a",
      "text": "재판관님, 제 친구의 연락 기록부터 확인해 주십시오. 경고였다는 말은 저는 한 번도 들은 적이 없습니다. 그리고 예전 손절 때부터 이어져 온 패턴도 같이 봐 주십시오.",
      "relatedDisputes": [
        "d-1",
        "d-4"
      ],
      "behaviorHint": "재판관에게 판정 순서를 요청하며 총정리한다."
    },
    {
      "speaker": "b",
      "text": "재판관님, 저는 연락한 사실을 숨기지 않겠습니다. 다만 제 친구가 확인 없이 단톡방에 먼저 퍼뜨린 부분도 같이 기록해 주십시오.",
      "relatedDisputes": [
        "d-1",
        "d-5"
      ],
      "behaviorHint": "재판관에게 공정한 분리 판단을 호소한다."
    }
  ]
}