{
  "caseId": "case-tenant-12",
  "dialogues": [
    {
      "speaker": "system",
      "text": "작은 다가구주택에서 이웃 세입자들 사이에 '4층 세입자가 문제'라는 소문이 돌기 시작했다. 세입자 이소담은 집주인 문경수가 관리인을 통해 소문을 퍼뜨렸다고 믿었고, 경수는 관리인이 알아서 설명한 것일 뿐이라고 했다.",
      "relatedDisputes": [],
      "behaviorHint": null
    },
    {
      "speaker": "a",
      "text": "재판관님, 옆집 이웃이 저한테 직접 말했어요. '관리인한테 들었는데, 4층이 문제라고 관리실에서 보고 있대.' 그 말이 누구한테서 나왔는지부터 확인해야 합니다.",
      "relatedDisputes": ["d-1", "d-2"],
      "behaviorHint": "'그 말 누가 처음 보냈죠'라고 끊으며 발신자를 고정하려 한다."
    },
    {
      "speaker": "b",
      "text": "재판관님, 그건 관리인이 응대한 겁니다. 저는 소담씨를 문제 세입자라고 말한 적 없어요. 미령씨가 민원을 처리하면서 그렇게 전달된 모양인데, 저한테 직접 물어보셨으면 바로 설명했을 겁니다.",
      "relatedDisputes": ["d-1", "d-2"],
      "behaviorHint": "'그건 관리인이 응대한 겁니다'를 반복해 자신의 책임선을 뒤로 밀어낸다."
    },
    {
      "speaker": "a",
      "text": "경수씨, 관리인은 경수씨 사람이잖아요. 관리인이 '4층 분 건은 조용히 보고 있다'고 말했는데, 그걸 듣고도 바로잡지 않으셨잖아요. 건물 단톡에 캡처까지 돌고 있었거든요.",
      "relatedDisputes": ["d-1", "d-3"],
      "behaviorHint": "캡처 여러 장을 한꺼번에 보여주며 증거를 쥐고 있다는 분위기를 만든다."
    },
    {
      "speaker": "b",
      "text": "재판관님, 미령씨 발언의 취지는 '확인 중'이라는 뜻이었어요. 문제 세입자라고 낙인찍으려는 것이 아니었는데, 그렇게 전달된 모양입니다. 저도 이전 세입자 때 소문이 빨리 번지는 걸 봤지만, 이번에 늦게 안 건 사실입니다.",
      "relatedDisputes": ["d-2", "d-4"],
      "behaviorHint": "'그렇게 전달된 모양' 같은 수동형 표현으로 행위 주체를 흐린다."
    },
    {
      "speaker": "a",
      "text": "재판관님, 저는 이 건물에서 계속 살아야 하는 사람이에요. 이웃들이 저를 피하기 시작했어요. 출처를 확인하기 전이라서 저도 단톡방에 해명 글을 올렸는데, 그게 잘못인가요?",
      "relatedDisputes": ["d-3", "d-5"],
      "behaviorHint": "억울해지면 질문이 끝나기 전에 끼어들어 사실과 해석을 한 번에 쏟아낸다."
    },
    {
      "speaker": "b",
      "text": "재판관님, 소담씨가 올린 글에는 '집주인이 세입자를 찍어서 소문 냈다'고 적혀 있었습니다. 확인도 안 하고 공개적으로 그렇게 쓰시면 제 평판도 문제가 됩니다. 저는 직접 퍼뜨린 적이 없어요.",
      "relatedDisputes": ["d-3", "d-5"],
      "behaviorHint": "잠깐 침묵한 뒤 원칙과 관리 규칙을 짧게 읽는다."
    },
    {
      "speaker": "system",
      "text": "소문의 직접 출처, 관리인 발언의 취지, 소담의 공개 반박, 실제 민원 수준, 쌍방 평판 피해 — 다섯 가지 쟁점이 관리인의 애매한 한마디에서 갈라진다.",
      "relatedDisputes": [],
      "behaviorHint": null
    },
    {
      "speaker": "a",
      "text": "재판관님, 저는 소문이 경수씨한테서 나온 줄 알았어요. 관리인이 혼자 그런 말을 할 이유가 없으니까요. 확인 전에 글을 올린 건 성급했을 수도 있어요. 하지만 소문을 바로잡지 않은 건 경수씨 책임 아닌가요.",
      "relatedDisputes": ["d-1", "d-4", "d-5"],
      "behaviorHint": "확인된 사실과 추정을 한 문장에 섞어 공격적으로 들린다."
    },
    {
      "speaker": "b",
      "text": "재판관님, 관리인 말 한마디까지 제가 통제해야 한다면 건물 운영이 안 됩니다. 저는 소담씨를 찍어 퍼뜨린 적 없고, 관리 규칙대로 민원을 처리한 것뿐입니다. 공개 단톡방에서 건물주를 비방한 부분은 소담씨가 정리하셔야 합니다.",
      "relatedDisputes": ["d-1", "d-3", "d-5"],
      "behaviorHint": "감정이 올라오면 잠깐 침묵한 뒤 원칙만 짧게 읽어 내려간다."
    }
  ]
}