{
  "caseId": "case-partner-01",
  "partyA": {
    "name": "이서준",
    "age": 38,
    "occupation": "생활용품 브랜드 공동대표 겸 운영총괄",
    "archetype": "cold_logic",
    "speechStyle": "질문을 받으면 감정 대신 숫자와 계약 단계부터 정리해 말한다. 불리해지면 '그건 구조상 불가피했다'며 판단의 여지를 줄이고, 상대의 감정적 표현을 절차 문제로 환원하려 한다.",
    "fear": "회사를 살리려다 횡령한 대표처럼 보이거나, 자금 판단을 통제하지 못한 운영자로 평가받는 것",
    "verbalTells": [
      {
        "trigger": "lying",
        "pattern": "핵심 의도를 묻는 질문이 나오면 계약 문구와 숫자를 길게 인용해 본심 설명을 뒤로 미룬다."
      },
      {
        "trigger": "cornered",
        "pattern": "자신이 정한 시간순서대로만 답하겠다며 질문의 초점을 다시 배열하려 든다."
      },
      {
        "trigger": "avoiding",
        "pattern": "상대가 배신감을 말하면 '감정은 별개고 구조를 보자'며 정서적 쟁점을 절차 문제로 납작하게 만든다."
      }
    ]
  },
  "partyB": {
    "name": "윤해나",
    "age": 35,
    "occupation": "생활용품 브랜드 공동대표 겸 영업브랜딩 총괄",
    "archetype": "confrontational",
    "speechStyle": "처음에는 질문보다 결론을 앞세워 단정하고, 상대가 머뭇거리면 같은 문장을 어조만 바꿔 반복한다. 유리한 정황 하나를 잡으면 맥락 전체를 이미 증명한 듯 몰아붙인다.",
    "fear": "매출 하락기에 회사 돈이 빠져나가는 걸 몰랐던 얼굴로 남거나, 공동대표인데도 최종 승인 없이 끌려갔다고 보이는 것",
    "verbalTells": [
      {
        "trigger": "lying",
        "pattern": "세부 사실보다 '결국 돈을 뺐다는 거네' 같은 헤드라인 결론을 먼저 던진다."
      },
      {
        "trigger": "cornered",
        "pattern": "같은 질문을 짧게 세 번쯤 반복하며 상대의 표정 변화로 빈틈을 찾으려 한다."
      },
      {
        "trigger": "emotional",
        "pattern": "불리한 앞뒤 맥락은 자르고 가장 자극적인 한 줄만 계속 되짚는다."
      }
    ]
  },
  "context": {
    "description": "브랜드 2주년 행사를 막 끝낸 시점이었지만, 실제 매출은 석 달 연속 빠지고 있었다. 직원 사기와 거래처 신뢰를 동시에 붙잡아야 하는 압박 속에서 두 사람은 외부 자금 유치 준비를 비공식적으로 서두르다가, 결과가 흔들리자 서로가 먼저 책임을 떼어내려 들었다."
  },
  "disputes": [
    {
      "id": "d-1",
      "name": "서준의 무단 예치금 송금"
    },
    {
      "id": "d-2",
      "name": "예치금은 서준의 개인 채무 상환이었는가"
    },
    {
      "id": "d-3",
      "name": "해나의 사전 구두 동의 번복"
    },
    {
      "id": "d-4",
      "name": "해나의 회계분류 지시 은폐"
    },
    {
      "id": "d-5",
      "name": "비환급 법률검토비의 실제 규모"
    }
  ]
}